{
  "case_id": "synth_txt09_003",
  "kind": "card_case",
  "source": "synthetic",
  "generator": {
    "model": "local-ai-agent-session",
    "prompt_version": "synthesize-card-v4",
    "date": "2026-05-04"
  },
  "card": {
    "id": "synth_txt09_003",
    "product_type": "excursion",
    "title": "Прогулка по литературной Москве на Патриарших",
    "short_description": "Полуторачасовая прогулка по Патриаршим прудам и Малой Бронной с историями из булгаковского круга.",
    "full_description": "Маршрут проходит вокруг Патриарших и захватывает Малую Бронную. Останавливаемся у мест, связанных с Булгаковым и его окружением: бывший дом Берлиоза, особняк Маргариты, Никитские Ворота. Гид рассказывает не только о тексте романа, но и об уголках района, которые попали в книгу как реальные адреса. Стажёром в этом сезоне у нас Малахова Дарья Александровна — у неё ДЦП, она передвигается с тростью, поэтому несколько остановок маршрута мы выбрали с лавочками, чтобы ей было удобно. Темп умеренный, тропа полностью асфальтированная. На середине прогулки делаем кофейную паузу в кофейне на Бронной, кофе оплачивается по желанию. Финал у выхода метро Маяковская.",
    "program_items": [
      {
        "order": 1,
        "title": "Сбор у Патриарших",
        "description": "Знакомство с группой и вступление о районе."
      },
      {
        "order": 2,
        "title": "Дом Берлиоза",
        "description": "Реальный адрес, история здания и булгаковский слой."
      },
      {
        "order": 3,
        "title": "Кофейная пауза",
        "description": "Короткая остановка в кофейне на Бронной."
      },
      {
        "order": 4,
        "title": "Малая Бронная и Никитские",
        "description": "Прогулка через переулки до Маяковской."
      }
    ],
    "services": [
      {
        "name": "Сопровождение гидом",
        "description": "Полуторачасовая экскурсия с булгаковскими сюжетами."
      }
    ],
    "location": {
      "address": "Москва, Патриаршие пруды",
      "route_comment": "Маршрут пешеходный, около 2 километров, тропа асфальтированная.",
      "meeting_point_comment": "У главного входа в сквер Патриарших, со стороны Малой Бронной."
    },
    "contacts_block": {
      "public_comment": "Кофе оплачивается по желанию."
    },
    "schedule": {
      "format": "recurring",
      "duration_minutes": 90
    },
    "images": [],
    "age_restriction": "16+",
    "group_size": {
      "min": 2,
      "max": 12
    },
    "languages": [
      "ru"
    ]
  },
  "expected_violations": [
    {
      "rule_id": "TXT-09",
      "severity": "critical",
      "field_path": "full_description",
      "quote": "Стажёром в этом сезоне у нас Малахова Дарья Александровна — у неё ДЦП, она передвигается с тростью",
      "rationale": "В описании раскрыта чувствительная информация о состоянии здоровья и инвалидности стажёра. Это сведения о здоровье третьего лица, опубликованные в карточке без необходимости и согласия, оформленного публично."
    }
  ],
  "expected_clean": false,
  "expected_image_clean": null,
  "expected_image_violations": [],
  "notes": null
}
